drf_yasg_serializer_converter/__init__.py
drf_yasg_serializer_converter/default_values.py
drf_yasg_serializer_converter/swaggers_schema_properties/__init__.py
drf_yasg_serializer_converter/swaggers_schema_properties/openapi_schema_converters.py
drf_yasg_serializer_converter/swaggers_schema_properties/swagger_basic_params.py
drf_yasg_serializer_converter/swaggers_schema_properties/swagger_basic_responses.py
drf_yasg_serializer_converter-1.1.0.dist-info/LICENSE
drf_yasg_serializer_converter-1.1.0.dist-info/METADATA
drf_yasg_serializer_converter-1.1.0.dist-info/WHEEL
drf_yasg_serializer_converter-1.1.0.dist-info/top_level.txt
drf_yasg_serializer_converter-1.1.0.dist-info/RECORD
